LICENSE
MANIFEST.in
README.md
requirements.txt
setup.py
simpleaws/__init__.py
simpleaws/simpleaws.py
simpleaws.egg-info/PKG-INFO
simpleaws.egg-info/SOURCES.txt
simpleaws.egg-info/dependency_links.txt
simpleaws.egg-info/requires.txt
simpleaws.egg-info/top_level.txt