Metadata-Version: 1.0
Name: simpleaws
Version: 0.1.1.1
Summary: Idiot proof AWS services.
Home-page: https://github.com/Miserlou/simpleaws
Author: Rich Jones
Author-email: rich@openwatch.net
License: MIT License
Platform: UNKNOWN
Classifier: Environment :: Web Environment
Classifier: Intended Audience :: Developers
Classifier: License :: OSI Approved :: Apache Software License
Classifier: Operating System :: OS Independent
Classifier: Programming Language :: Python
Classifier: Programming Language :: Python :: 2.6
Classifier: Programming Language :: Python :: 2.7
Classifier: Topic :: Internet :: WWW/HTTP
Classifier: Topic :: Internet :: WWW/HTTP :: Dynamic Content
